MANIFEST.in
README.md
setup.py
portinus/__init__.py
portinus/cli.py
portinus/composesource.py
portinus/environmentfile.py
portinus/restart.py
portinus/service.py
portinus.egg-info/PKG-INFO
portinus.egg-info/SOURCES.txt
portinus.egg-info/dependency_links.txt
portinus.egg-info/entry_points.txt
portinus.egg-info/requires.txt
portinus.egg-info/top_level.txt
portinus/monitor/__init__.py
portinus/monitor/checker.py
portinus/monitor/cli.py
portinus/templates/instance.service
portinus/templates/monitor.service
portinus/templates/monitor.timer
portinus/templates/restart.service
portinus/templates/restart.timer
portinus/templates/service-script