Metadata-Version: 1.1
Name: portinus
Version: 1.0.17
Summary: This utility creates a systemd service file for a docker-compose file
Home-page: https://github.com/justin8/portinus
Author: Justin Dray
Author-email: justin@dray.be
License: MIT
Platform: UNKNOWN
Classifier: Operating System :: OS Independent
Classifier: Programming Language :: Python :: 3 :: Only
Classifier: Programming Language :: Python :: 3
Classifier: Environment :: Console
Classifier: License :: OSI Approved :: MIT License
Classifier: Development Status :: 5 - Production/Stable
Classifier: Programming Language :: Python
